README.txt
setup.cfg
setup.py
cs/__init__.py
cs.migration.folder2donedukia.egg-info/PKG-INFO
cs.migration.folder2donedukia.egg-info/SOURCES.txt
cs.migration.folder2donedukia.egg-info/dependency_links.txt
cs.migration.folder2donedukia.egg-info/entry_points.txt
cs.migration.folder2donedukia.egg-info/namespace_packages.txt
cs.migration.folder2donedukia.egg-info/not-zip-safe
cs.migration.folder2donedukia.egg-info/requires.txt
cs.migration.folder2donedukia.egg-info/top_level.txt
cs/migration/__init__.py
cs/migration/folder2donedukia/__init__.py
cs/migration/folder2donedukia/configure.zcml
cs/migration/folder2donedukia/tests.py
cs/migration/folder2donedukia/version.txt
cs/migration/folder2donedukia/browser/__init__.py
cs/migration/folder2donedukia/browser/configure.zcml
cs/migration/folder2donedukia/browser/folder.py
docs/HISTORY.txt
docs/INSTALL.txt
docs/LICENSE.GPL
docs/LICENSE.txt