Metadata-Version: 1.1
Name: cs.migration.folder2donedukia
Version: 1.6
Summary: UNKNOWN
Home-page: http://svn.plone.org/svn/plone/plone.app.example
Author: Mikel Larreategi
Author-email: mlarreategi@codesyntax.com
License: GPL
Platform: UNKNOWN
Classifier: Framework :: Plone
Classifier: Programming Language :: Python
Classifier: Topic :: Software Development :: Libraries :: Python Modules
